MANIFEST.in
README.md
requirements.txt
setup.cfg
setup.py
EMS/__init__.py
EMS/exaManagementSystem.py
EMS/data/captionnames.tex
EMS/data/exam-french.cls
EMS/data/exam-german.cls
EMS/data/exam.cfg
EMS/data/sms.sty
EMS/data/solution.cls
EMS/data/logos/A_global_nb.jpg
EMS/data/logos/UNF_Logo_100pr_pos.pdf
EMS/utils/LaTeX.py
EMS/utils/Utils.py
EMS/utils/ZipUtils.py
EMS/utils/__init__.py
etc/exaManagementSystem-completion.bash
etc/logging.conf
exaManagementSystem.egg-info/PKG-INFO
exaManagementSystem.egg-info/SOURCES.txt
exaManagementSystem.egg-info/dependency_links.txt
exaManagementSystem.egg-info/entry_points.txt
exaManagementSystem.egg-info/requires.txt
exaManagementSystem.egg-info/top_level.txt