Metadata-Version: 1.1
Name: exaManagementSystem
Version: 1.1.15
Summary: Manages Series
Home-page: https://github.com/digsim/exaManagementSystem
Author: Andreas Ruppen
Author-email: andreas.ruppen@gmail.com
License: Apache
Keywords: students series
Platform: any
Classifier: Development Status :: 5 - Production/Stable
Classifier: Environment :: Console
Classifier: Intended Audience :: Education
Classifier: Intended Audience :: End Users/Desktop
Classifier: Intended Audience :: Science/Research
Classifier: Topic :: Utilities
Classifier: Topic :: Education
Classifier: Topic :: Software Development :: Compilers
Classifier: License :: OSI Approved :: Apache Software License
Classifier: Operating System :: MacOS :: MacOS X
Classifier: Operating System :: POSIX
Classifier: Programming Language :: Python :: 2
Classifier: Programming Language :: Python :: 2.6
Classifier: Programming Language :: Python :: 2.7
Classifier: Programming Language :: Python :: 3
Classifier: Programming Language :: Python :: 3.2
Classifier: Programming Language :: Python :: 3.3
Classifier: Programming Language :: Python :: 3.4
